docs/AccountsApi.md
docs/Achievement.md
docs/AchievementTypeEnum.md
docs/AchievementsApi.md
docs/AlertsApi.md
docs/CallbackTokenAuth.md
docs/CallbackTokenAuthRequest.md
docs/CameraSnapshot.md
docs/CrashReport.md
docs/CrashReportStatusEnum.md
docs/CrashReportsApi.md
docs/DemoFeedbackEnum.md
docs/DemoSubmission.md
docs/DemoSubmissionFeedbackRequest.md
docs/DemosApi.md
docs/DevicesApi.md
docs/DjStripeCharge.md
docs/DjStripeCheckoutSession.md
docs/DjStripeCustomer.md
docs/DjStripePaymentIntent.md
docs/DjStripePrice.md
docs/DjStripeProduct.md
docs/EmailAlertSettings.md
docs/EmailAlertSettingsRequest.md
docs/EmailAuth.md
docs/EmailAuthRequest.md
docs/EmailWaitlist.md
docs/EmailWaitlistRequest.md
docs/ErrorDetail.md
docs/EventSourceEnum.md
docs/EventTypeEnum.md
docs/EventTypesEnum.md
docs/GcodeFile.md
docs/InterestEnum.md
docs/JanusApi.md
docs/JanusConfigType.md
docs/LoginRequest.md
docs/MoonrakerApi.md
docs/MoonrakerServer.md
docs/MoonrakerServerRequest.md
docs/NatsOrganization.md
docs/NatsOrganizationRequest.md
docs/NatsOrganizationUser.md
docs/NetworkSettings.md
docs/NetworkSettingsRequest.md
docs/OctoPrintBackup.md
docs/OctoPrintServer.md
docs/OctoPrintServerRequest.md
docs/OctoPrintSettings.md
docs/OctoPrintSettingsRequest.md
docs/OctoPrinterProfile.md
docs/OctoPrinterProfileRequest.md
docs/OctoprintApi.md
docs/Order.md
docs/OrderCheckoutRequest.md
docs/OrderItemRequest.md
docs/OrderStatus.md
docs/OrderStatusType.md
docs/PaginatedAchievementList.md
docs/PaginatedCameraSnapshotList.md
docs/PaginatedCrashReportList.md
docs/PaginatedGcodeFileList.md
docs/PaginatedMoonrakerServerList.md
docs/PaginatedOctoPrintBackupList.md
docs/PaginatedOctoPrintServerList.md
docs/PaginatedOctoPrintSettingsList.md
docs/PaginatedOctoPrinterProfileList.md
docs/PaginatedPiList.md
docs/PaginatedPrintJobAlertList.md
docs/PaginatedProductList.md
docs/PaginatedSystemInfoList.md
docs/PaginatedVideoRecordingList.md
docs/PaginatedVideoRecordingPartList.md
docs/PaginatedWebrtcStreamList.md
printnanny_api_client-0.135.1.dist-info/METADATA
printnanny_api_client-0.135.1.dist-info/WHEEL
printnanny_api_client-0.135.1.dist-info/top_level.txt
printnanny_api_client-0.135.1.dist-info/RECORD
