Metadata-Version: 2.1
Name: printnanny-api-client
Version: 0.135.1
Summary: printnanny-api-client
Home-page: UNKNOWN
Author: Leigh Johnson
Author-email: leigh@printnanny.ai
License: AGPLv3
Keywords: OpenAPI,OpenAPI-Generator,printnanny-api-client
Platform: UNKNOWN
Requires-Dist: aiohttp (<3.8,>=3.7.0)
Requires-Dist: protobuf
Requires-Dist: python-dateutil
Requires-Dist: six (>=1.10)
Requires-Dist: urllib3 (>=1.25.3)
